sw_mcp/cli.py
sw_mcp/cursor.py
sw_mcp/llm.py
sw_mcp/server.py
sw_mcp/solidworks.py
sw_mcp/types.py
sw_mcp/utils.py
denso_mcp-0.4.2.dist-info/METADATA
denso_mcp-0.4.2.dist-info/WHEEL
denso_mcp-0.4.2.dist-info/entry_points.txt
denso_mcp-0.4.2.dist-info/licenses/license.rtf
denso_mcp-0.4.2.dist-info/RECORD
