Metadata-Version: 2.4
Name: denso-mcp
Version: 0.4.2
Summary: Add your description here
Author-email: Vaibhav Jain <vaibhav@aiplanet.com>
License-File: license.rtf
Requires-Python: >=3.10
Requires-Dist: agno>=1.5.6
Requires-Dist: aiohttp>=3.11.18
Requires-Dist: anthropic>=0.52.1
Requires-Dist: boto3>=1.38.27
Requires-Dist: comtypes>=1.4.11
Requires-Dist: fastmcp>=2.5.2
Requires-Dist: google-genai>=1.16.1
Requires-Dist: ipython>=8.36.0
Requires-Dist: keyboard>=0.13.5
Requires-Dist: langchain-aws>=0.2.24
Requires-Dist: langchain-mcp-adapters>=0.1.4
Requires-Dist: langgraph>=0.4.7
Requires-Dist: matplotlib>=3.10.3
Requires-Dist: mcp>=1.9.2
Requires-Dist: opencv-python>=4.11.0.86
Requires-Dist: pyautogui>=0.9.54
Requires-Dist: python-dotenv>=1.1.0
Requires-Dist: pythonnet>=3.0.5
Requires-Dist: pywin32>=310
Requires-Dist: streamlit>=1.45.0
